stemgen/__init__.py
stemgen/__main__.py
stemgen/ableton.py
stemgen/cli.py
stemgen/metadata.json
stemgen/metadata.py
stemgen/pretty_collection.py
stemgen/pretty_history.py
stemgen/pretty_playlists.py
stemgen/stem.py
stemgen/stemcopy.py
stemgen/stemsep.py
stemgen/stemtag.py
stemgen/ni-stem/_internal.py
stemgen/ni-stem/ni-stem
stemgen/ni-stem/GPAC_linux/MP4Box
stemgen/ni-stem/GPAC_linux/gm_ft_font.so
stemgen/ni-stem/GPAC_linux/gm_validator.so
stemgen/ni-stem/GPAC_linux/gm_x11_out.so
stemgen/ni-stem/GPAC_linux/gpac
stemgen/ni-stem/GPAC_linux/libgpac.so
stemgen/ni-stem/GPAC_linux/libgpac.so.12
stemgen/ni-stem/GPAC_linux/libgpac.so.12.12.0
stemgen/ni-stem/GPAC_linux/libgpac_static.a
stemgen/ni-stem/GPAC_mac/mp4box
stemgen/ni-stem/GPAC_mac/lib/libSDL2-2.0.0.dylib
stemgen/ni-stem/GPAC_mac/lib/liba52.0.dylib
stemgen/ni-stem/GPAC_mac/lib/libass.9.dylib
stemgen/ni-stem/GPAC_mac/lib/libavcodec.58.dylib
stemgen/ni-stem/GPAC_mac/lib/libavdevice.58.dylib
stemgen/ni-stem/GPAC_mac/lib/libavfilter.7.dylib
stemgen/ni-stem/GPAC_mac/lib/libavformat.58.dylib
stemgen/ni-stem/GPAC_mac/lib/libavresample.4.dylib
stemgen/ni-stem/GPAC_mac/lib/libavutil.56.dylib
stemgen/ni-stem/GPAC_mac/lib/libbluray.2.dylib
stemgen/ni-stem/GPAC_mac/lib/libcrypto.1.1.dylib
stemgen/ni-stem/GPAC_mac/lib/libfaad.2.dylib
stemgen/ni-stem/GPAC_mac/lib/libffi.7.dylib
stemgen/ni-stem/GPAC_mac/lib/libfontconfig.1.dylib
stemgen/ni-stem/GPAC_mac/lib/libfreetype.6.dylib
stemgen/ni-stem/GPAC_mac/lib/libfribidi.0.dylib
stemgen/ni-stem/GPAC_mac/lib/libgif.dylib
stemgen/ni-stem/GPAC_mac/lib/libglib-2.0.0.dylib
stemgen/ni-stem/GPAC_mac/lib/libgmp.10.dylib
stemgen/ni-stem/GPAC_mac/lib/libgnutls.30.dylib
stemgen/ni-stem/GPAC_mac/lib/libgpac.dylib
stemgen/ni-stem/GPAC_mac/lib/libgraphite2.3.dylib
stemgen/ni-stem/GPAC_mac/lib/libharfbuzz.0.dylib
stemgen/ni-stem/GPAC_mac/lib/libhogweed.6.dylib
stemgen/ni-stem/GPAC_mac/lib/libidn2.0.dylib
stemgen/ni-stem/GPAC_mac/lib/libintl.8.dylib
stemgen/ni-stem/GPAC_mac/lib/libjpeg.9.dylib
stemgen-2.1.0.dist-info/METADATA
stemgen-2.1.0.dist-info/WHEEL
stemgen-2.1.0.dist-info/entry_points.txt
stemgen-2.1.0.dist-info/top_level.txt
stemgen-2.1.0.dist-info/RECORD
