Metadata-Version: 2.4
Name: stemgen
Version: 2.1.0
Summary: Stemgen is a Stem file generator. Convert any track into a stem and have fun with Traktor.
Home-page: https://stemgen.dev
Author: Axel Delafosse
Author-email: axeldelafosse@gmail.com
License: MIT
Classifier: Programming Language :: Python :: 3
Classifier: License :: OSI Approved :: MIT License
Classifier: Operating System :: OS Independent
Requires-Python: >=3.9
Requires-Dist: Lossless-BS-RoFormer
Requires-Dist: mutagen
Requires-Dist: torch
Requires-Dist: soundfile
Requires-Dist: pyloudnorm
Requires-Dist: traktor-nml-utils
Requires-Dist: pyautogui
Requires-Dist: pylive
Requires-Dist: opencv-python
Requires-Dist: ffmpeg-python
Requires-Dist: pywinauto; platform_system == "Windows"
Requires-Dist: pyobjc-core; platform_system == "Darwin"
Requires-Dist: pyobjc; platform_system == "Darwin"
Requires-Dist: Pillow; platform_system == "Darwin"
